airac_tools/__init__.py
airac_tools/cycle.py
airac_tools/utils.py
airac_tools-1.0.11.dist-info/licenses/LICENSE
airac_tools-1.0.11.dist-info/METADATA
airac_tools-1.0.11.dist-info/WHEEL
airac_tools-1.0.11.dist-info/top_level.txt
airac_tools-1.0.11.dist-info/RECORD
