Metadata-Version: 2.4
Name: airac-tools
Version: 1.0.11
Summary: Utilities for working with ICAO AIRAC cycles, including cycle calculations, validation, and conversions.
Author-email: Juan José Sánchez <pip@jjsm.science>
License: MIT License
Project-URL: Homepage, https://github.com/jj-sm/airac-tools
Project-URL: Repository, https://github.com/jj-sm/airac-tools
Project-URL: Issues, https://github.com/jj-sm/airac-tools/issues
Classifier: Programming Language :: Python :: 3
Classifier: Programming Language :: Python :: 3.8
Classifier: Programming Language :: Python :: 3.9
Classifier: Programming Language :: Python :: 3.10
Classifier: Programming Language :: Python :: 3.11
Classifier: Programming Language :: Python :: 3.12
Classifier: License :: OSI Approved :: MIT License
Classifier: Operating System :: OS Independent
Classifier: Intended Audience :: Developers
Classifier: Topic :: Software Development :: Libraries :: Python Modules
Requires-Python: >=3.8
License-File: LICENSE
Dynamic: license-file
